vsplit/__init__.py
vsplit/chunk.py
vsplit/cli.py
vsplit/fs.py
vsplit/splitter.py
vsplit/vars.py
vsplit-0.1.4.dist-info/METADATA
vsplit-0.1.4.dist-info/WHEEL
vsplit-0.1.4.dist-info/entry_points.txt
vsplit-0.1.4.dist-info/licenses/LICENSE
vsplit-0.1.4.dist-info/RECORD
