Metadata-Version: 2.4
Name: vsplit
Version: 0.1.4
Summary: Virtually split a file based on a pattern.
Project-URL: Homepage, https://virologyCharite.github.io/vsplit/
Project-URL: Repository, https://github.com/virologyCharite/vsplit
Author-email: Terry Jones <terence.jones@charite.de>
License-File: LICENSE
Keywords: python
Classifier: Intended Audience :: Developers
Classifier: Programming Language :: Python
Classifier: Programming Language :: Python :: 3
Classifier: Programming Language :: Python :: 3.9
Classifier: Programming Language :: Python :: 3.10
Classifier: Programming Language :: Python :: 3.11
Classifier: Programming Language :: Python :: 3.12
Classifier: Programming Language :: Python :: 3.13
Classifier: Topic :: Software Development :: Libraries :: Python Modules
Requires-Python: <4.0,>=3.9
